layerpack/__init__.py
layerpack/cli.py
layerpack/dependency_manager.py
layerpack/exceptions.py
layerpack/layer_builder.py
layerpack/logger.py
layerpack/packager.py
layerpack-0.1.2.dist-info/LICENSE
layerpack-0.1.2.dist-info/METADATA
layerpack-0.1.2.dist-info/WHEEL
layerpack-0.1.2.dist-info/entry_points.txt
layerpack-0.1.2.dist-info/RECORD
