Metadata-Version: 2.3
Name: layerpack
Version: 0.1.2
Summary: A Python library for simplifying AWS Lambda deployment
License: MIT
Author: Richard
Author-email: richardkiscoding@gmail.com
Requires-Python: >=3.9,<3.14
Classifier: Development Status :: 3 - Alpha
Classifier: Intended Audience :: Developers
Classifier: License :: OSI Approved :: MIT License
Classifier: Programming Language :: Python :: 3
Classifier: Programming Language :: Python :: 3.9
Classifier: Programming Language :: Python :: 3.10
Classifier: Programming Language :: Python :: 3.11
Classifier: Programming Language :: Python :: 3.12
Classifier: Programming Language :: Python :: 3.13
Requires-Dist: click (>=8.0.0,<9.0.0)
Requires-Dist: packaging (>=23.2,<24.0)
Requires-Dist: poetry (>=1.7.0,<2.0.0)
Requires-Dist: poetry-core (>=1.9.0,<2.0.0)
Requires-Dist: setuptools (>=69.0.0,<70.0.0)
Requires-Dist: uv (>=0.1.7,<0.2.0)
